{
  "purpose": "FB Stories image pool",
  "description": "DuberyMNL FB story rotation -- curated 9:16 favorites (Fathers Day 2026 refresh).",
  "channel": "facebook-stories",
  "consumer": "tools/facebook/story_rotation.py",
  "rotation": "time-based, every 4 hours via GitHub Actions cron",
  "saved_at": "2026-04-16T14:02:34",
  "updated_at": "2026-06-16T19:32:27",
  "count": 57,
  "picks": [
    {
      "file": "duo-swimming-9x16.png",
      "type": "person",
      "model": "mixed",
      "path": "contents/assets/stories-fd-2026-06/duo-swimming-9x16.png",
      "source": "contents/new/duo-swimming.png",
      "story_9x16": true,
      "added_at": "2026-06-16T12:53:06"
    },
    {
      "file": "duo-hiking-9x16.png",
      "type": "person",
      "model": "mixed",
      "path": "contents/assets/stories-fd-2026-06/duo-hiking-9x16.png",
      "source": "contents/new/duo-hiking.png",
      "story_9x16": true,
      "added_at": "2026-06-16T12:53:06"
    },
    {
      "file": "2026-06-16_hz-hook-9x16.png",
      "type": "person",
      "model": "mixed",
      "path": "contents/assets/stories-fd-2026-06/2026-06-16_hz-hook-9x16.png",
      "source": "contents/new/2026-06-16_hz-hook.png",
      "story_9x16": true,
      "added_at": "2026-06-16T12:53:06"
    },
    {
      "file": "2026-06-16_hz3-hook-9x16.png",
      "type": "person",
      "model": "mixed",
      "path": "contents/assets/stories-fd-2026-06/2026-06-16_hz3-hook-9x16.png",
      "source": "contents/new/2026-06-16_hz3-hook.png",
      "story_9x16": true,
      "added_at": "2026-06-16T12:53:06"
    },
    {
      "file": "2026-06-16_fd-02-outback-black-boardwalk-armaround-9x16.png",
      "type": "person",
      "model": "outback-black",
      "path": "contents/assets/stories-fd-2026-06/2026-06-16_fd-02-outback-black-boardwalk-armaround-9x16.png",
      "source": "contents/new/2026-06-16_fd-02-outback-black-boardwalk-armaround.png",
      "story_9x16": true,
      "added_at": "2026-06-16T12:53:06"
    },
    {
      "file": "2026-06-16_fd-03-bandits-matte-black-backyard-laugh-9x16.png",
      "type": "person",
      "model": "bandits-matte-black",
      "path": "contents/assets/stories-fd-2026-06/2026-06-16_fd-03-bandits-matte-black-backyard-laugh-9x16.png",
      "source": "contents/new/2026-06-16_fd-03-bandits-matte-black-backyard-laugh.png",
      "story_9x16": true,
      "added_at": "2026-06-16T12:53:06"
    },
    {
      "file": "2026-06-16_fd-06-bandits-blue-courtside-fanenergy-9x16.png",
      "type": "person",
      "model": "bandits-blue",
      "path": "contents/assets/stories-fd-2026-06/2026-06-16_fd-06-bandits-blue-courtside-fanenergy-9x16.png",
      "source": "contents/new/2026-06-16_fd-06-bandits-blue-courtside-fanenergy.png",
      "story_9x16": true,
      "added_at": "2026-06-16T12:53:06"
    },
    {
      "file": "fdo-fishing-9x16.png",
      "type": "person",
      "model": "mixed",
      "path": "contents/assets/stories-fd-2026-06/fdo-fishing-9x16.png",
      "source": "contents/new/fdo-fishing.png",
      "story_9x16": true,
      "added_at": "2026-06-16T12:53:06"
    },
    {
      "file": "fd-beach-A-9x16.png",
      "type": "person",
      "model": "mixed",
      "path": "contents/assets/stories-fd-2026-06/fd-beach-A-9x16.png",
      "source": "contents/new/fd-beach-A.png",
      "story_9x16": true,
      "added_at": "2026-06-16T12:53:06"
    },
    {
      "file": "fd-park-A-9x16.png",
      "type": "person",
      "model": "mixed",
      "path": "contents/assets/stories-fd-2026-06/fd-park-A-9x16.png",
      "source": "contents/new/fd-park-A.png",
      "story_9x16": true,
      "added_at": "2026-06-16T12:53:06"
    },
    {
      "file": "2026-06-16_fathers_day_bespoke_v2_1-9x16.png",
      "type": "person",
      "model": "mixed",
      "path": "contents/assets/stories-fd-2026-06/2026-06-16_fathers_day_bespoke_v2_1-9x16.png",
      "source": "contents/new/2026-06-16_fathers_day_bespoke_v2_1.png",
      "story_9x16": true,
      "added_at": "2026-06-16T12:53:06"
    },
    {
      "file": "2026-06-16_fathers_day_bespoke_v4_3-9x16.png",
      "type": "person",
      "model": "mixed",
      "path": "contents/assets/stories-fd-2026-06/2026-06-16_fathers_day_bespoke_v4_3-9x16.png",
      "source": "contents/new/2026-06-16_fathers_day_bespoke_v4_3.png",
      "story_9x16": true,
      "added_at": "2026-06-16T12:53:06"
    },
    {
      "file": "2026-06-16_fathers_day_bespoke_v6_1-9x16.png",
      "type": "person",
      "model": "mixed",
      "path": "contents/assets/stories-fd-2026-06/2026-06-16_fathers_day_bespoke_v6_1-9x16.png",
      "source": "contents/new/2026-06-16_fathers_day_bespoke_v6_1.png",
      "story_9x16": true,
      "added_at": "2026-06-16T12:53:06"
    },
    {
      "file": "card-1-9x16.png",
      "type": "brand",
      "model": "mixed",
      "path": "contents/assets/stories-fd-2026-06/card-1-9x16.png",
      "source": "contents/new/fdhz-cards/card-1.png",
      "story_9x16": true,
      "added_at": "2026-06-16T12:53:06"
    },
    {
      "file": "card-4-9x16.png",
      "type": "brand",
      "model": "mixed",
      "path": "contents/assets/stories-fd-2026-06/card-4-9x16.png",
      "source": "contents/new/fdhz-cards/card-4.png",
      "story_9x16": true,
      "added_at": "2026-06-16T12:53:06"
    },
    {
      "file": "card-5-9x16.png",
      "type": "brand",
      "model": "mixed",
      "path": "contents/assets/stories-fd-2026-06/card-5-9x16.png",
      "source": "contents/new/fdhz-cards/card-5.png",
      "story_9x16": true,
      "added_at": "2026-06-16T12:53:06"
    },
    {
      "file": "card-3-9x16.png",
      "type": "brand",
      "model": "mixed",
      "path": "contents/assets/stories-fd-2026-06/card-3-9x16.png",
      "source": "contents/new/fdhz-cards-2/card-3.png",
      "story_9x16": true,
      "added_at": "2026-06-16T12:53:06"
    },
    {
      "file": "card-6-9x16.png",
      "type": "brand",
      "model": "mixed",
      "path": "contents/assets/stories-fd-2026-06/card-6-9x16.png",
      "source": "contents/new/fdhz-cards-sku2/card-6.png",
      "story_9x16": true,
      "added_at": "2026-06-16T12:53:06"
    },
    {
      "file": "2026-05-31_outback-black-hero-4pair-v2-9x16.png",
      "type": "product",
      "model": "outback-black",
      "path": "contents/assets/stories-fd-2026-06/2026-05-31_outback-black-hero-4pair-v2-9x16.png",
      "source": "contents/new/2026-05-31_outback-black-hero-4pair-v2.png",
      "story_9x16": true,
      "added_at": "2026-06-16T12:53:06"
    },
    {
      "file": "2026-05-24_y2k-10-bandits-tortoise-goldenhour-9x16.png",
      "type": "person",
      "model": "bandits-tortoise",
      "path": "contents/assets/stories-fd-2026-06/2026-05-24_y2k-10-bandits-tortoise-goldenhour-9x16.png",
      "source": "contents/new/2026-05-24_y2k-10-bandits-tortoise-goldenhour.png",
      "story_9x16": true,
      "added_at": "2026-06-16T12:53:06"
    },
    {
      "file": "2026-05-26_bespoke_outback_blue_iconic-v2-9x16.png",
      "type": "product",
      "model": "outback-blue",
      "path": "contents/assets/stories-fd-2026-06/2026-05-26_bespoke_outback_blue_iconic-v2-9x16.png",
      "source": "contents/new/2026-05-26_bespoke_outback_blue_iconic-v2.png",
      "story_9x16": true,
      "added_at": "2026-06-16T12:53:06"
    },
    {
      "file": "2026-05-27_v2_couple_blue_x_red_03-9x16.png",
      "type": "person",
      "model": "mixed",
      "path": "contents/assets/stories-fd-2026-06/2026-05-27_v2_couple_blue_x_red_03-9x16.png",
      "source": "contents/new/2026-05-27_v2_couple_blue_x_red_03.png",
      "story_9x16": true,
      "added_at": "2026-06-16T12:53:06"
    },
    {
      "file": "2026-05-28_hsb-10-rasta-red-9x16.png",
      "type": "person",
      "model": "rasta-red",
      "path": "contents/assets/stories-fd-2026-06/2026-05-28_hsb-10-rasta-red-9x16.png",
      "source": "contents/new/2026-05-28_hsb-10-rasta-red.png",
      "story_9x16": true,
      "added_at": "2026-06-16T12:53:06"
    },
    {
      "file": "2026-06-03_fishing-action-v10-9x16.png",
      "type": "person",
      "model": "mixed",
      "path": "contents/assets/stories-fd-2026-06/2026-06-03_fishing-action-v10-9x16.png",
      "source": "contents/new/2026-06-03_fishing-action-v10.png",
      "story_9x16": true,
      "added_at": "2026-06-16T12:53:06"
    },
    {
      "file": "2026-05-04_bespoke-bandits-green-editorial-v2-9x16.png",
      "type": "brand",
      "model": "bandits-green",
      "path": "contents/assets/stories-fd-2026-06/2026-05-04_bespoke-bandits-green-editorial-v2-9x16.png",
      "source": "contents/ready/ads/2026-05-04_bespoke-bandits-green-editorial-v2.png",
      "story_9x16": true,
      "added_at": "2026-06-16T12:53:06"
    },
    {
      "file": "2026-06-16_hz4-blue-9x16.png",
      "type": "person",
      "model": "mixed",
      "path": "contents/assets/stories-fd-2026-06/2026-06-16_hz4-blue-9x16.png",
      "source": "contents/new/2026-06-16_hz4-blue.png",
      "story_9x16": true,
      "added_at": "2026-06-16T12:53:06"
    },
    {
      "file": "act-fishing-9x16.png",
      "type": "person",
      "model": "mixed",
      "path": "contents/assets/stories-fd-2026-06/act-fishing-9x16.png",
      "source": "contents/new/act-fishing.png",
      "story_9x16": true,
      "added_at": "2026-06-16T12:53:06"
    },
    {
      "file": "act-surfing-9x16.png",
      "type": "person",
      "model": "mixed",
      "path": "contents/assets/stories-fd-2026-06/act-surfing-9x16.png",
      "source": "contents/new/act-surfing.png",
      "story_9x16": true,
      "added_at": "2026-06-16T12:53:06"
    },
    {
      "file": "act-hiking-9x16.png",
      "type": "person",
      "model": "mixed",
      "path": "contents/assets/stories-fd-2026-06/act-hiking-9x16.png",
      "source": "contents/new/act-hiking.png",
      "story_9x16": true,
      "added_at": "2026-06-16T12:53:06"
    },
    {
      "file": "duo-camping-9x16.png",
      "type": "person",
      "model": "mixed",
      "path": "contents/assets/stories-fd-2026-06/duo-camping-9x16.png",
      "source": "contents/new/duo-camping.png",
      "story_9x16": true,
      "added_at": "2026-06-16T12:53:06"
    },
    {
      "file": "duo-roadtrip-9x16.png",
      "type": "person",
      "model": "mixed",
      "path": "contents/assets/stories-fd-2026-06/duo-roadtrip-9x16.png",
      "source": "contents/new/duo-roadtrip.png",
      "story_9x16": true,
      "added_at": "2026-06-16T12:53:06"
    },
    {
      "file": "fdo-cafe-9x16.png",
      "type": "person",
      "model": "mixed",
      "path": "contents/assets/stories-fd-2026-06/fdo-cafe-9x16.png",
      "source": "contents/new/fdo-cafe.png",
      "story_9x16": true,
      "added_at": "2026-06-16T12:53:06"
    },
    {
      "file": "fdo-walk-9x16.png",
      "type": "person",
      "model": "mixed",
      "path": "contents/assets/stories-fd-2026-06/fdo-walk-9x16.png",
      "source": "contents/new/fdo-walk.png",
      "story_9x16": true,
      "added_at": "2026-06-16T12:53:06"
    },
    {
      "file": "fd-beach-B-9x16.png",
      "type": "person",
      "model": "mixed",
      "path": "contents/assets/stories-fd-2026-06/fd-beach-B-9x16.png",
      "source": "contents/new/fd-beach-B.png",
      "story_9x16": true,
      "added_at": "2026-06-16T12:53:06"
    },
    {
      "file": "fd-fishing-B-9x16.png",
      "type": "person",
      "model": "mixed",
      "path": "contents/assets/stories-fd-2026-06/fd-fishing-B-9x16.png",
      "source": "contents/new/fd-fishing-B.png",
      "story_9x16": true,
      "added_at": "2026-06-16T12:53:06"
    },
    {
      "file": "fd-pier-B-9x16.png",
      "type": "person",
      "model": "mixed",
      "path": "contents/assets/stories-fd-2026-06/fd-pier-B-9x16.png",
      "source": "contents/new/fd-pier-B.png",
      "story_9x16": true,
      "added_at": "2026-06-16T12:53:06"
    },
    {
      "file": "2026-06-16_fd-04-outback-red-jeepney-lolo-9x16.png",
      "type": "person",
      "model": "outback-red",
      "path": "contents/assets/stories-fd-2026-06/2026-06-16_fd-04-outback-red-jeepney-lolo-9x16.png",
      "source": "contents/new/2026-06-16_fd-04-outback-red-jeepney-lolo.png",
      "story_9x16": true,
      "added_at": "2026-06-16T12:53:06"
    },
    {
      "file": "2026-06-16_fd-05-rasta-brown-mall-plaza-daughter-9x16.png",
      "type": "person",
      "model": "rasta-brown",
      "path": "contents/assets/stories-fd-2026-06/2026-06-16_fd-05-rasta-brown-mall-plaza-daughter-9x16.png",
      "source": "contents/new/2026-06-16_fd-05-rasta-brown-mall-plaza-daughter.png",
      "story_9x16": true,
      "added_at": "2026-06-16T12:53:06"
    },
    {
      "file": "2026-06-16_fathers_day_bespoke_v2_2-9x16.png",
      "type": "person",
      "model": "mixed",
      "path": "contents/assets/stories-fd-2026-06/2026-06-16_fathers_day_bespoke_v2_2-9x16.png",
      "source": "contents/new/2026-06-16_fathers_day_bespoke_v2_2.png",
      "story_9x16": true,
      "added_at": "2026-06-16T12:53:06"
    },
    {
      "file": "2026-06-16_fathers_day_bespoke_v2_7-9x16.png",
      "type": "person",
      "model": "mixed",
      "path": "contents/assets/stories-fd-2026-06/2026-06-16_fathers_day_bespoke_v2_7-9x16.png",
      "source": "contents/new/2026-06-16_fathers_day_bespoke_v2_7.png",
      "story_9x16": true,
      "added_at": "2026-06-16T12:53:06"
    },
    {
      "file": "2026-06-16_fathers_day_bespoke_v3_2-9x16.png",
      "type": "person",
      "model": "mixed",
      "path": "contents/assets/stories-fd-2026-06/2026-06-16_fathers_day_bespoke_v3_2-9x16.png",
      "source": "contents/new/2026-06-16_fathers_day_bespoke_v3_2.png",
      "story_9x16": true,
      "added_at": "2026-06-16T12:53:06"
    },
    {
      "file": "2026-06-16_fathers_day_bespoke_v4_5-9x16.png",
      "type": "person",
      "model": "mixed",
      "path": "contents/assets/stories-fd-2026-06/2026-06-16_fathers_day_bespoke_v4_5-9x16.png",
      "source": "contents/new/2026-06-16_fathers_day_bespoke_v4_5.png",
      "story_9x16": true,
      "added_at": "2026-06-16T12:53:06"
    },
    {
      "file": "2026-06-16_fathers_day_bespoke_v6_3-9x16.png",
      "type": "person",
      "model": "mixed",
      "path": "contents/assets/stories-fd-2026-06/2026-06-16_fathers_day_bespoke_v6_3-9x16.png",
      "source": "contents/new/2026-06-16_fathers_day_bespoke_v6_3.png",
      "story_9x16": true,
      "added_at": "2026-06-16T12:53:06"
    },
    {
      "file": "card-2-9x16.png",
      "type": "brand",
      "model": "mixed",
      "path": "contents/assets/stories-fd-2026-06/card-2-9x16.png",
      "source": "contents/new/fdhz-cards/card-2.png",
      "story_9x16": true,
      "added_at": "2026-06-16T12:53:06"
    },
    {
      "file": "card-3-9x16.png",
      "type": "brand",
      "model": "mixed",
      "path": "contents/assets/stories-fd-2026-06/card-3-9x16.png",
      "source": "contents/new/fdhz-cards/card-3.png",
      "story_9x16": true,
      "added_at": "2026-06-16T12:53:06"
    },
    {
      "file": "card-6-9x16.png",
      "type": "brand",
      "model": "mixed",
      "path": "contents/assets/stories-fd-2026-06/card-6-9x16.png",
      "source": "contents/new/fdhz-cards/card-6.png",
      "story_9x16": true,
      "added_at": "2026-06-16T12:53:06"
    },
    {
      "file": "card-2-9x16.png",
      "type": "brand",
      "model": "mixed",
      "path": "contents/assets/stories-fd-2026-06/card-2-9x16.png",
      "source": "contents/new/fdhz-cards-2/card-2.png",
      "story_9x16": true,
      "added_at": "2026-06-16T12:53:06"
    },
    {
      "file": "card-2-9x16.png",
      "type": "brand",
      "model": "mixed",
      "path": "contents/assets/stories-fd-2026-06/card-2-9x16.png",
      "source": "contents/new/fdhz-cards-sku2/card-2.png",
      "story_9x16": true,
      "added_at": "2026-06-16T12:53:06"
    },
    {
      "file": "2026-05-31_bandits-green-hero-5pair-9x16.png",
      "type": "product",
      "model": "bandits-green",
      "path": "contents/assets/stories-fd-2026-06/2026-05-31_bandits-green-hero-5pair-9x16.png",
      "source": "contents/new/2026-05-31_bandits-green-hero-5pair.png",
      "story_9x16": true,
      "added_at": "2026-06-16T12:53:06"
    },
    {
      "file": "2026-05-31_outback-red-hero-5pair-9x16.png",
      "type": "product",
      "model": "outback-red",
      "path": "contents/assets/stories-fd-2026-06/2026-05-31_outback-red-hero-5pair-9x16.png",
      "source": "contents/new/2026-05-31_outback-red-hero-5pair.png",
      "story_9x16": true,
      "added_at": "2026-06-16T12:53:06"
    },
    {
      "file": "2026-05-31_bandits-tortoise-hero-4pair-9x16.png",
      "type": "product",
      "model": "bandits-tortoise",
      "path": "contents/assets/stories-fd-2026-06/2026-05-31_bandits-tortoise-hero-4pair-9x16.png",
      "source": "contents/new/2026-05-31_bandits-tortoise-hero-4pair.png",
      "story_9x16": true,
      "added_at": "2026-06-16T12:53:06"
    },
    {
      "file": "2026-05-31_rasta-red-hero-3pair-v2-9x16.png",
      "type": "product",
      "model": "rasta-red",
      "path": "contents/assets/stories-fd-2026-06/2026-05-31_rasta-red-hero-3pair-v2-9x16.png",
      "source": "contents/new/2026-05-31_rasta-red-hero-3pair-v2.png",
      "story_9x16": true,
      "added_at": "2026-06-16T12:53:06"
    },
    {
      "file": "2026-05-22_poster_08_outback_black_road-9x16.png",
      "type": "brand",
      "model": "outback-black",
      "path": "contents/assets/stories-fd-2026-06/2026-05-22_poster_08_outback_black_road-9x16.png",
      "source": "contents/new/2026-05-22_poster_08_outback_black_road.png",
      "story_9x16": true,
      "added_at": "2026-06-16T12:53:06"
    },
    {
      "file": "2026-05-22_poster_10_outback_green_clearly-9x16.png",
      "type": "brand",
      "model": "outback-green",
      "path": "contents/assets/stories-fd-2026-06/2026-05-22_poster_10_outback_green_clearly-9x16.png",
      "source": "contents/new/2026-05-22_poster_10_outback_green_clearly.png",
      "story_9x16": true,
      "added_at": "2026-06-16T12:53:06"
    },
    {
      "file": "2026-05-24_y2k-tight-08-bandits-blue-fullsend-9x16.png",
      "type": "person",
      "model": "bandits-blue",
      "path": "contents/assets/stories-fd-2026-06/2026-05-24_y2k-tight-08-bandits-blue-fullsend-9x16.png",
      "source": "contents/new/2026-05-24_y2k-tight-08-bandits-blue-fullsend.png",
      "story_9x16": true,
      "added_at": "2026-06-16T12:53:06"
    },
    {
      "file": "2026-05-27_v2_closeup_red_01-9x16.png",
      "type": "product",
      "model": "mixed",
      "path": "contents/assets/stories-fd-2026-06/2026-05-27_v2_closeup_red_01-9x16.png",
      "source": "contents/new/2026-05-27_v2_closeup_red_01.png",
      "story_9x16": true,
      "added_at": "2026-06-16T12:53:06"
    },
    {
      "file": "2026-05-04_bespoke-outback-blue-graphic-c1-9x16.png",
      "type": "brand",
      "model": "outback-blue",
      "path": "contents/assets/stories-fd-2026-06/2026-05-04_bespoke-outback-blue-graphic-c1-9x16.png",
      "source": "contents/ready/ads/2026-05-04_bespoke-outback-blue-graphic-c1.png",
      "story_9x16": true,
      "added_at": "2026-06-16T12:53:06"
    }
  ]
}